{
  "project_info": {
    "project_number": "88729508985",
    "firebase_url": "https://spottrade-171321.firebaseio.com",
    "project_id": "spottrade-171321",
    "storage_bucket": "spottrade-171321.appspot.com"
  },
  "client": [
    {
      "client_info": {
        "mobilesdk_app_id": "1:88729508985:android:e4acca3f26e40c05",
        "android_client_info": {
          "package_name": "almanza1112.spottrade"
        }
      },
      "oauth_client": [
        {
          "client_id": "88729508985-mp379a72jtgi9hivgvaedgg5sa7s8p7i.apps.googleusercontent.com",
          "client_type": 3
        }
      ],
      "api_key": [
        {
          "current_key": "AIzaSyApJ5q9sUytj2uZaB6ULoIZPzeD-Bzpa_s"
        }
      ],
      "services": {
        "analytics_service": {
          "status": 1
        },
        "appinvite_service": {
          "status": 1,
          "other_platform_oauth_client": []
        },
        "ads_service": {
          "status": 2
        }
      }
    }
  ],
  "configuration_version": "1"
}